{
  "time": "2026-07-13 08:30",
  "indices": {
    "sh000001": {
      "name": "",
      "price": 3913.79,
      "prev": 3996.16,
      "pct": -2.06,
      "vol": 590907356,
      "amt": 1334871933909.0,
      "high": 3983.05,
      "low": 3900.67
    },
    "sz399001": {
      "name": "",
      "price": 14522.85,
      "prev": 15046.67,
      "pct": -3.48,
      "vol": 733844798,
      "amt": 1482889150433.4329,
      "high": 14997.07,
      "low": 14437.07
    },
    "sz399006": {
      "name": "",
      "price": 3723.52,
      "prev": 3842.73,
      "pct": -3.1,
      "vol": 226532308,
      "amt": 696341242509.56,
      "high": 3855.75,
      "low": 3691.23
    }
  },
  "picks": [],
  "sectors": [],
  "global": {
    "us": [
      {
        "name": "道琼斯",
        "price": 52637.01,
        "pct": 0.29
      },
      {
        "name": "纳斯达克",
        "price": 26281.61,
        "pct": 0.29
      },
      {
        "name": "标普500",
        "price": 7575.39,
        "pct": 0.42
      },
      {
        "name": "恒生",
        "price": 24213.72,
        "pct": 0.16
      },
      {
        "name": "日经",
        "price": 67242.73,
        "pct": -1.92
      }
    ],
    "usStocks": [
      {
        "name": "苹果",
        "price": 3153.2,
        "pct": -0.28
      },
      {
        "name": "微软",
        "price": 3851.0,
        "pct": 0.19
      },
      {
        "name": "英伟达",
        "price": 2109.6,
        "pct": 4.03
      },
      {
        "name": "特斯拉",
        "price": 4077.6,
        "pct": 0.3
      },
      {
        "name": "谷歌",
        "price": 3550.3,
        "pct": -0.34
      },
      {
        "name": "亚马逊",
        "price": 2453.4,
        "pct": -0.69
      },
      {
        "name": "Meta",
        "price": 6692.1,
        "pct": 5.97
      },
      {
        "name": "AMD",
        "price": 5578.9,
        "pct": 2.04
      }
    ]
  }
}